{
	"info": {
		"_postman_id": "822fb28d-9bc1-4649-85c5-65dca1278f43",
		"name": "Library API Collection",
		"schema": "https://schema.getpostman.com/json/collection/v2.1.0/collection.json",
		"_exporter_id": "47470486",
		"_collection_link": "https://aeysha-arobi-8830215.postman.co/workspace/Week-6-API-Testing~bc6b115a-9395-4017-bbe1-0f52202ede21/collection/47470486-822fb28d-9bc1-4649-85c5-65dca1278f43?action=share&source=collection_link&creator=47470486"
	},
	"item": [
		{
			"name": "Create Book",
			"event": [
				{
					"listen": "test",
					"script": {
						"exec": [
							"pm.test(\"Status code is 201\", function () {\r",
							"    pm.response.to.have.status(201);\r",
							"});\r",
							"\r",
							"pm.test(\"Response contains book ID\", function () {\r",
							"    var jsonData = pm.response.json();\r",
							"    pm.expect(jsonData).to.have.property(\"id\");\r",
							"    // save id for next requests\r",
							"    pm.collectionVariables.set(\"bookId\", jsonData.id);\r",
							"});\r",
							""
						],
						"type": "text/javascript",
						"packages": {}
					}
				},
				{
					"listen": "prerequest",
					"script": {
						"exec": [
							"// generate random year between 1950 and 2025\r",
							"let randomYear = Math.floor(Math.random() * (2025 - 1950 + 1)) + 1950;\r",
							"pm.collectionVariables.set(\"randomYear\", randomYear);\r",
							""
						],
						"type": "text/javascript",
						"packages": {}
					}
				}
			],
			"request": {
				"method": "POST",
				"header": [
					{
						"key": "api-key",
						"value": "{{apiKey}}",
						"type": "text"
					},
					{
						"key": "Content-Type",
						"value": "application/json",
						"type": "text"
					}
				],
				"body": {
					"mode": "raw",
					"raw": "{\r\n  \"title\": \"Book {{$randomInt}}\",\r\n  \"author\": \"Author {{$randomFirstName}}\",\r\n  \"genre\": \"Genre {{$randomWord}}\",\r\n  \"yearPublished\": {{randomYear}}\r\n}",
					"options": {
						"raw": {
							"language": "json"
						}
					}
				},
				"url": {
					"raw": "{{baseUrl}}/books",
					"host": [
						"{{baseUrl}}"
					],
					"path": [
						"books"
					]
				}
			},
			"response": []
		},
		{
			"name": "Update Book",
			"event": [
				{
					"listen": "test",
					"script": {
						"exec": [
							"pm.test(\"Status code is 200\", function () {\r",
							"    pm.response.to.have.status(200);\r",
							"});\r",
							"\r",
							"pm.test(\"Title updated\", function () {\r",
							"    var jsonData = pm.response.json();\r",
							"    pm.expect(jsonData.title).to.include(\"Updated\");\r",
							"});\r",
							""
						],
						"type": "text/javascript",
						"packages": {}
					}
				},
				{
					"listen": "prerequest",
					"script": {
						"exec": [
							""
						],
						"type": "text/javascript",
						"packages": {}
					}
				}
			],
			"request": {
				"method": "PATCH",
				"header": [
					{
						"key": "api-key",
						"value": "{{apiKey}}",
						"type": "text"
					},
					{
						"key": "Content-Type",
						"value": "application/json",
						"type": "text"
					}
				],
				"body": {
					"mode": "raw",
					"raw": "{\r\n    \"title\": \"Updated Book {{$randomInt}}\"\r\n}",
					"options": {
						"raw": {
							"language": "json"
						}
					}
				},
				"url": {
					"raw": "{{baseUrl}}/books/{{bookId}}",
					"host": [
						"{{baseUrl}}"
					],
					"path": [
						"books",
						"{{bookId}}"
					]
				}
			},
			"response": []
		},
		{
			"name": "Delete Book",
			"event": [
				{
					"listen": "test",
					"script": {
						"exec": [
							"pm.test(\"Status code is 204\", function () {\r",
							"    pm.response.to.have.status(204);\r",
							"});\r",
							"\r",
							""
						],
						"type": "text/javascript",
						"packages": {}
					}
				},
				{
					"listen": "prerequest",
					"script": {
						"exec": [
							""
						],
						"type": "text/javascript",
						"packages": {}
					}
				}
			],
			"request": {
				"method": "DELETE",
				"header": [
					{
						"key": "api-key",
						"value": "{{apiKey}}",
						"type": "text"
					}
				],
				"url": {
					"raw": "{{baseUrl}}/books/{{bookId}}",
					"host": [
						"{{baseUrl}}"
					],
					"path": [
						"books",
						"{{bookId}}"
					]
				}
			},
			"response": []
		}
	],
	"event": [
		{
			"listen": "prerequest",
			"script": {
				"type": "text/javascript",
				"packages": {},
				"exec": [
					""
				]
			}
		},
		{
			"listen": "test",
			"script": {
				"type": "text/javascript",
				"packages": {},
				"exec": [
					""
				]
			}
		}
	],
	"variable": [
		{
			"key": "baseUrl",
			"value": ""
		},
		{
			"key": "apiKey",
			"value": ""
		},
		{
			"key": "bookId",
			"value": ""
		},
		{
			"key": "randomYear",
			"value": ""
		}
	]
}